{
  "id": "irctc-sbi-platinum",
  "issuer": "SBI Card",
  "name": "IRCTC SBI Platinum Card",
  "imageUrl": "/images/irctc-sbi-platinum.png",
  "network": [
    "Visa"
  ],
  "joiningFee": 500,
  "annualFee": 500,
  "feeWaiverSpend": null,
  "bestFor": [
    "railway",
    "irctc",
    "travel",
    "railway lounge",
    "low fee"
  ],
  "rewardType": "reward points",
  "rewardLiquidity": "brand-locked",
  "rewards": [
    {
      "category": "travel",
      "displayCategory": "Eligible AC rail ticket bookings on IRCTC",
      "rate": 8,
      "displayRate": "10 Reward Points / Rs 125 spent",
      "capMonthly": null
    },
    {
      "category": "base",
      "displayCategory": "Other eligible non-fuel retail purchases",
      "rate": 0.8,
      "displayRate": "1 Reward Point / Rs 125 spent",
      "capMonthly": null
    }
  ],
  "loungeDomestic": 4,
  "loungeInternational": 0,
  "lounge": {
    "domestic": [
      "4 complimentary railway lounge visits per year in India, capped at 1 per quarter, for the primary cardholder."
    ]
  },
  "forexMarkup": 3.5,
  "tags": [
    "irctc",
    "railway",
    "travel",
    "railway lounge",
    "low fee"
  ],
  "exclusions": [
    "fuel",
    "cash withdrawal",
    "fees and charges",
    "disputed transactions"
  ],
  "exclusionCodes": [
    "fuel",
    "cash_withdrawal",
    "fees_and_charges",
    "disputed_transactions"
  ],
  "joiningBenefitsValued": [
    {
      "value": 350,
      "kind": "points",
      "label": "350 activation bonus Reward Points on a single transaction of Rs 500 or more within 60 days of card issuance"
    }
  ],
  "renewalBenefitsValued": [
    {
      "value": 500,
      "kind": "points",
      "label": "500 Reward Points on payment of renewal fee"
    }
  ],
  "joiningBenefits": [
    "350 activation bonus Reward Points on a single transaction of Rs 500 or more within 60 days of card issuance"
  ],
  "renewalBenefits": [
    "500 Reward Points on payment of renewal fee"
  ],
  "milestoneBenefits": [],
  "additionalBenefits": [
    "Save 1% transaction charges on eligible railway ticket bookings on IRCTC",
    "1% fuel surcharge waiver on eligible fuel transactions, capped at Rs 100 per statement cycle"
  ],
  "redemption": {
    "ecosystemLabel": "IRCTC railway ticket bookings",
    "ecosystemValue": 1,
    "pointsExpiryYears": 2
  },
  "eligibility": {
    "salaried": [
      "Age 21 to 60 years",
      "Stable income as per SBI Card credit assessment",
      "Good credit profile and address in a serviced location"
    ],
    "selfEmployed": [
      "Age 25 to 60 years",
      "Stable business income as per SBI Card credit assessment",
      "Good credit profile and address in a serviced location"
    ]
  },
  "additionalDetails": [],
  "internalNotes": [
    "Audited against official IRCTC SBI Platinum product page and IRCTC offer page on 2026-06-08.",
    "The 10% value-back framing comes from 10 Reward Points per Rs 125 on eligible AC1, AC2, AC3, Executive Chair Car, and Chair Car bookings via IRCTC app or website.",
    "Reward Points accrued in the SBI Card account will not get credited to the IRCTC loyalty account if the loyalty account status is blocked, inactive, or suspended.",
    "Card details manually reviewed and verified by user on 2026-06-09."
  ],
  "supportingSourceUrls": [
    "https://www.sbicard.com/en/personal/credit-cards/travel/irctc-sbi-platinum-card.page",
    "https://www.sbicard.com/en/personal/offers/travel/irctc-sbi-platinum-card.page"
  ],
  "sourceUrl": "https://www.sbicard.com/en/personal/credit-cards/travel/irctc-sbi-platinum-card.page",
  "applyUrl": "https://www.sbicard.com/en/personal/credit-cards/travel/irctc-sbi-platinum-card.page",
  "lastVerified": "2026-06-09",
  "verificationStatus": "official-direct",
  "popularityScore": 72
}
