{
  "id": "indusind-tiger",
  "issuer": "IndusInd Bank",
  "name": "Tiger Credit Card",
  "network": [
    "Visa"
  ],
  "joiningFee": 0,
  "annualFee": 0,
  "feeWaiverSpend": null,
  "bestFor": [
    "travel",
    "lounge",
    "golf",
    "movies",
    "low forex"
  ],
  "rewardType": "reward points",
  "rewards": [
    {
      "category": "utilities, insurance, government, education, real estate, rent",
      "displayCategory": "Utility, insurance, government, education, real estate, and rent spends",
      "rate": 1,
      "displayRate": "1 point per ₹100",
      "capMonthly": null
    },
    {
      "category": "base",
      "displayCategory": "Base spends (up to ₹1L)",
      "rate": 1,
      "displayRate": "1 point per ₹100",
      "capMonthly": null,
      "tierLowerBound": 0,
      "tierUpperBound": 8333
    },
    {
      "category": "base",
      "displayCategory": "Base spends (₹1.01L - 2.5L)",
      "rate": 2,
      "displayRate": "2 points per ₹100",
      "capMonthly": null,
      "tierLowerBound": 8333,
      "tierUpperBound": 20833
    },
    {
      "category": "base",
      "displayCategory": "Base spends (₹2.51L - 5L)",
      "rate": 4,
      "displayRate": "4 points per ₹100",
      "capMonthly": null,
      "tierLowerBound": 20833,
      "tierUpperBound": 41667
    },
    {
      "category": "base",
      "displayCategory": "Base spends (above ₹5L)",
      "rate": 6,
      "displayRate": "6 points per ₹100",
      "capMonthly": null,
      "tierLowerBound": 41667,
      "tierUpperBound": null
    }
  ],
  "popularityScore": 100,
  "loungeDomestic": 8,
  "loungeInternational": 2,
  "lounge": {
    "international": [
      "Priority Pass membership is complimentary ($99 value), but visits beyond the 2 complimentary visits are charged at standard rates."
    ]
  },
  "forexMarkup": 1.5,
  "tags": [
    "indusind",
    "tiger",
    "travel",
    "lounge",
    "golf",
    "movies",
    "low forex",
    "lifetime free"
  ],
  "exclusions": [
    "fuel",
    "cash advances"
  ],
  "exclusionCodes": [
    "fuel",
    "cash_advance"
  ],
  "milestoneBenefits": [],
  "additionalBenefits": [
    "1 complimentary golf game or lesson per quarter",
    "1 complimentary movie ticket up to ₹500 every 6 months on BookMyShow",
    "Auto Assist roadside emergency services (breakdown, key replacement, flat tire)"
  ],
  "additionalDetails": [
    "Cash redemption is capped at 5,000 reward points per calendar month"
  ],
  "redemption": {
    "statementBalanceValue": 0.4,
    "airMilesValue": 1,
    "pointsExpiryYears": null,
    "airlinePartners": [
      {
        "airline": "Singapore Airlines",
        "programme": "KrisFlyer",
        "ratio": "4:1"
      },
      {
        "airline": "Air India",
        "programme": "Maharaja Club",
        "ratio": "1:1",
        "notes": "Capped at 25,000 reward points per month; transfer via IndusMoments portal"
      }
    ]
  },
  "eligibility": {
    "salaried": [
      "Eligibility is subject to IndusInd Bank approval criteria"
    ],
    "selfEmployed": [
      "Eligibility is subject to IndusInd Bank approval criteria"
    ]
  },
  "internalNotes": [
    "Card details manually reviewed and verified by user on 2026-06-14.",
    "Reward Points redemption towards InterMiles discontinued effective 21st January, 2025.",
    "Priority Pass membership is complimentary ($99 value), but visits beyond the 2 complimentary visits are charged at standard rates.",
    "[2026-06-14] Air India Maharaja Club added as airline partner at 1:1 ratio (1 reward point = 1 Maharaja Club point), capped at 25,000 points per month, transferred via IndusMoments portal."
  ],
  "sourceUrl": "https://www.indusind.bank.in/in/en/personal/cards/credit-card/tiger-credit-card.html",
  "applyUrl": "https://www.indusind.bank.in/in/en/personal/cards/credit-card/tiger-credit-card.html",
  "affiliateUrl": "https://bitli.in/PqBnzn5",
  "lastVerified": "2026-06-14",
  "verificationStatus": "official-direct",
  "imageUrl": "/images/indusind-tiger.webp"
}
