{
  "id": "sc-easemytrip",
  "issuer": "Standard Chartered",
  "name": "EaseMyTrip Credit Card",
  "network": [
    "Visa"
  ],
  "joiningFee": 350,
  "annualFee": 350,
  "feeWaiverSpend": 50000,
  "bestFor": [
    "travel",
    "hotel",
    "flight",
    "low fee"
  ],
  "rewardType": "360° Rewards points and instant discounts",
  "rewards": [
    {
      "category": "travel",
      "rate": 10,
      "displayCategory": "Standalone hotel and airline spends",
      "displayRate": "10 reward points / ₹100 spent",
      "capMonthly": null
    },
    {
      "category": "base",
      "rate": 2,
      "displayCategory": "Other retail spends",
      "displayRate": "2 reward points / ₹100 spent",
      "capMonthly": null
    }
  ],
  "popularityScore": 79,
  "loungeDomestic": 4,
  "loungeInternational": 2,
  "lounge": {
    "domestic": [
      "1 complimentary domestic lounge visit per calendar quarter"
    ],
    "international": [
      "2 complimentary international lounge visits per calendar year"
    ]
  },
  "forexMarkup": 3.5,
  "tags": [
    "standard chartered",
    "easemytrip",
    "travel",
    "hotel",
    "flight",
    "co-branded"
  ],
  "exclusions": [
    "Cash withdrawal / cash advance transactions",
    "Fees and charges (including annual fee and finance charges)"
  ],
  "exclusionCodes": [
    "cash_advance"
  ],
  "milestones": [],
  "milestoneBenefits": [
    "Annual fee waiver on spends of ₹50,000 or more in the previous year"
  ],
  "additionalBenefits": [
    "20% instant discount on hotels and 10% off on flights on EaseMyTrip using promo code EMTSCB",
    "Flat ₹125 off on bus bookings (min transaction ₹500) on EaseMyTrip"
  ],
  "redemption": {
    "statementBalanceValue": 0.25,
    "redemptionFee": 99
  },
  "eligibility": {
    "salaried": [
      "Age: 18 to 65 years"
    ],
    "selfEmployed": [
      "Age: 18 to 67 years"
    ]
  },
  "imageUrl": "/images/sc-easemytrip.webp",
  "sourceUrl": "https://www.sc.com/in/credit-cards/easemytrip-credit-card/",
  "applyUrl": "https://www.sc.com/in/credit-cards/easemytrip-credit-card/",
  "lastVerified": "2026-06-14",
  "verificationStatus": "official-direct",
  "internalNotes": [
    "Card details manually reviewed and verified by user on 2026-06-14.",
    "10X rewards (10 points / ₹100) apply specifically to standalone airline and hotel bookings, excluding aggregators. Aggregators earn base rate.",
    "Base rate is 2 points / ₹100 spent (effectively 0.5% return value).",
    "EaseMyTrip discounts require using the promo code EMTSCB."
  ],
  "applyLinks": [
    {
      "url": "https://www.sc.com/in/credit-cards/easemytrip-credit-card/",
      "provider": "official"
    }
  ]
}
